turtleart/__init__.py
turtleart/draw.py
turtleart/scripts/__init__.py
turtleart/scripts/qturtle.py
turtleart-0.2.dist-info/DESCRIPTION.rst
turtleart-0.2.dist-info/METADATA
turtleart-0.2.dist-info/RECORD
turtleart-0.2.dist-info/WHEEL
turtleart-0.2.dist-info/entry_points.txt
turtleart-0.2.dist-info/metadata.json
turtleart-0.2.dist-info/top_level.txt
