Metadata-Version: 2.0
Name: turtleart
Version: 0.2
Summary: Library to facilitate Turtle Art
Home-page: UNKNOWN
Author: Ava and Teo Lisitza
Author-email: mlisitza+github@gmail.com
License: UNKNOWN
Platform: UNKNOWN
Requires-Dist: ipython
